verilog/xor.v
module XOR_GATE (
    input a, b,
    output y
);
    assign y = a ^ b;
endmodule

verilog/or5.v
module OR5_gate (
    input a, b, c, d, e,
    output y
);
    assign y = a | b | c | d | e;
endmodule

verilog/and5.v
module AND5_gate (
    input a, b, c, d, e,
    output y
);
    assign y = a & b & c & d & e;
endmodule

verilog/and4.v
module AND4_gate (
    input a, b, c, d,
    output y
);
    assign y = a & b & c & d;
endmodule

verilog/and3.v
module AND3_gate (
    input a, b, c,
    output y
);
    assign y = a & b & c;
endmodule

verilog/and.v
module AND_gate (
    input a, b,
    output y
);
    assign y = a & b;
endmodule

verilog/or4.v
module OR4_gate (
    input a, b, c, d,
    output y
);
    assign y = a | b | c | d;
endmodule

verilog/or3.v
module OR3_gate (
    input a, b, c,
    output y
);
    assign y = a | b | c;
endmodule

verilog/or.v
module OR_gate (
    input a, b,
    output y
);
    assign y = a | b;
endmodule

verilog/cla.v
module cla(
    input [3:0] A, B,
    input Cin,
    output [3:0] S,
    output [4:0] C
);
    wire [3:0] G, P;

    // generate and propogate 

    AND_gate and0 (.a(A[0]), .b(B[0]), .y(G[0]));
    AND_gate and1 (.a(A[1]), .b(B[1]), .y(G[1]));
    AND_gate and2 (.a(A[2]), .b(B[2]), .y(G[2]));
    AND_gate and3 (.a(A[3]), .b(B[3]), .y(G[3]));

    XOR_GATE xor0 (.a(A[0]), .b(B[0]), .y(P[0]));
    XOR_GATE xor1 (.a(A[1]), .b(B[1]), .y(P[1]));
    XOR_GATE xor2 (.a(A[2]), .b(B[2]), .y(P[2]));
    XOR_GATE xor3 (.a(A[3]), .b(B[3]), .y(P[3]));

    // carries
    assign C[0] = Cin;

    wire P0C0, P1G0, P1P0C0, P2G1, P2P1G0, P2P1P0C0, P3G2, P3P2G1, P3P2P1G0, P3P2P1P0C0;

    AND_gate and4 (.a(P[0]), .b(C[0]), .y(P0C0));
    OR_gate or0 (.a(G[0]), .b(P0C0), .y(C[1]));

    AND_gate and5 (.a(P[1]), .b(G[0]), .y(P1G0));
    AND3_gate and6 (.a(P[1]), .b(P[0]), .c(C[0]), .y(P1P0C0));
    OR3_gate or1 (.a(G[1]), .b(P1G0), .c(P1P0C0), .y(C[2]));

    AND_gate and7 (.a(P[2]), .b(G[1]), .y(P2G1));
    AND3_gate and8 (.a(P[2]), .b(P[1]), .c(G[0]), .y(P2P1G0));
    AND4_gate and9 (.a(P[2]), .b(P[1]), .c(P[0]), .d(C[0]), .y(P2P1P0C0));
    OR4_gate or2 (.a(G[2]), .b(P2G1), .c(P2P1G0), .d(P2P1P0C0), .y(C[3]));

    AND_gate and10 (.a(P[3]), .b(G[2]), .y(P3G2));
    AND3_gate and11 (.a(P[3]), .b(P[2]), .c(G[1]), .y(P3P2G1));
    AND4_gate and12 (.a(P[3]), .b(P[2]), .c(P[1]), .d(G[0]), .y(P3P2P1G0));
    AND5_gate and13 (.a(P[3]), .b(P[2]), .c(P[1]), .d(P[0]), .e(C[0]), .y(P3P2P1P0C0));
    OR5_gate or3 (.a(G[3]), .b(P3G2), .c(P3P2G1), .d(P3P2P1G0), .e(P3P2P1P0C0), .y(C[4]));

    // final ans
    XOR_GATE sum0 (.a(P[0]), .b(C[0]), .y(S[0]));
    XOR_GATE sum1 (.a(P[1]), .b(C[1]), .y(S[1]));
    XOR_GATE sum2 (.a(P[2]), .b(C[2]), .y(S[2]));
    XOR_GATE sum3 (.a(P[3]), .b(C[3]), .y(S[3]));

endmodule

verilog/clatb.v
module cla_tb;
    reg [3:0] A;
    reg [3:0] B;
    reg Cin;

    // outputs
    wire [3:0] S;
    wire [4:0] C;

    cla uut (
        .A(A), 
        .B(B), 
        .Cin(Cin), 
        .S(S), 
        .C(C)
    );

    initial begin
        A = 0;
        B = 0;
        Cin = 0;
        #30;
        A = 4'b0001; B = 4'b0010; Cin = 0; #10;
        A = 4'b0101; B = 4'b0110; Cin = 1; #10;
        A = 4'b1111; B = 4'b0001; Cin = 0; #10;
        A = 4'b1010; B = 4'b0101; Cin = 1; #10;
        A = 4'b1100; B = 4'b0011; Cin = 0; #10;
        A = 4'b1001; B = 4'b0110; Cin = 1; #10;
        A = 4'b1111; B = 4'b1111; Cin = 0; #10;
        A = 4'b1111; B = 4'b1111; Cin = 1; #10;
        A = 4'b0000; B = 4'b0000; Cin = 0; #10;
        A = 4'b0000; B = 4'b0000; Cin = 1; #10;
        A = 4'b0001; B = 4'b0001; Cin = 0; #10;
        A = 4'b0001; B = 4'b0001; Cin = 1; #10;
        A = 4'b0010; B = 4'b0010; Cin = 0; #10;
        A = 4'b0010; B = 4'b0010; Cin = 1; #10;
        A = 4'b0011; B = 4'b0011; Cin = 0; #10;
        A = 4'b0011; B = 4'b0011; Cin = 1; #10;
        A = 4'b0100; B = 4'b0100; Cin = 0; #10;
        A = 4'b0100; B = 4'b0100; Cin = 1; #10;

        $finish;
    end

    initial begin
        $monitor("At time %t, A = %b, B = %b, Cin = %b, S = %b, C = %b", $time, A, B, Cin, S, C);
        $dumpfile("clatb.vcd");
        $dumpvars(0, cla_tb);
    end
      
endmodule

verilog/clatb.vcd
$date
	Sat Nov  9 10:39:57 2024
$end
$version
	Icarus Verilog
$end
$timescale
	1s
$end
$scope module cla_tb $end
$var wire 4 ! S [3:0] $end
$var wire 5 " C [4:0] $end
$var reg 4 # A [3:0] $end
$var reg 4 $ B [3:0] $end
$var reg 1 % Cin $end
$scope module uut $end
$var wire 4 & A [3:0] $end
$var wire 4 ' B [3:0] $end
$var wire 1 % Cin $end
$var wire 4 ( S [3:0] $end
$var wire 1 ) P3P2P1P0C0 $end
$var wire 1 * P3P2P1G0 $end
$var wire 1 + P3P2G1 $end
$var wire 1 , P3G2 $end
$var wire 1 - P2P1P0C0 $end
$var wire 1 . P2P1G0 $end
$var wire 1 / P2G1 $end
$var wire 1 0 P1P0C0 $end
$var wire 1 1 P1G0 $end
$var wire 1 2 P0C0 $end
$var wire 4 3 P [3:0] $end
$var wire 4 4 G [3:0] $end
$var wire 5 5 C [4:0] $end
$scope module and0 $end
$var wire 1 6 a $end
$var wire 1 7 b $end
$var wire 1 8 y $end
$upscope $end
$scope module and1 $end
$var wire 1 9 a $end
$var wire 1 : b $end
$var wire 1 ; y $end
$upscope $end
$scope module and10 $end
$var wire 1 < a $end
$var wire 1 = b $end
$var wire 1 , y $end
$upscope $end
$scope module and11 $end
$var wire 1 > a $end
$var wire 1 ? b $end
$var wire 1 @ c $end
$var wire 1 + y $end
$upscope $end
$scope module and12 $end
$var wire 1 A a $end
$var wire 1 B b $end
$var wire 1 C c $end
$var wire 1 D d $end
$var wire 1 * y $end
$upscope $end
$scope module and13 $end
$var wire 1 E a $end
$var wire 1 F b $end
$var wire 1 G c $end
$var wire 1 H d $end
$var wire 1 I e $end
$var wire 1 ) y $end
$upscope $end
$scope module and2 $end
$var wire 1 J a $end
$var wire 1 K b $end
$var wire 1 L y $end
$upscope $end
$scope module and3 $end
$var wire 1 M a $end
$var wire 1 N b $end
$var wire 1 O y $end
$upscope $end
$scope module and4 $end
$var wire 1 P a $end
$var wire 1 Q b $end
$var wire 1 2 y $end
$upscope $end
$scope module and5 $end
$var wire 1 R a $end
$var wire 1 S b $end
$var wire 1 1 y $end
$upscope $end
$scope module and6 $end
$var wire 1 T a $end
$var wire 1 U b $end
$var wire 1 V c $end
$var wire 1 0 y $end
$upscope $end
$scope module and7 $end
$var wire 1 W a $end
$var wire 1 X b $end
$var wire 1 / y $end
$upscope $end
$scope module and8 $end
$var wire 1 Y a $end
$var wire 1 Z b $end
$var wire 1 [ c $end
$var wire 1 . y $end
$upscope $end
$scope module and9 $end
$var wire 1 \ a $end
$var wire 1 ] b $end
$var wire 1 ^ c $end
$var wire 1 _ d $end
$var wire 1 - y $end
$upscope $end
$scope module or0 $end
$var wire 1 ` a $end
$var wire 1 2 b $end
$var wire 1 a y $end
$upscope $end
$scope module or1 $end
$var wire 1 b a $end
$var wire 1 1 b $end
$var wire 1 0 c $end
$var wire 1 c y $end
$upscope $end
$scope module or2 $end
$var wire 1 d a $end
$var wire 1 / b $end
$var wire 1 . c $end
$var wire 1 - d $end
$var wire 1 e y $end
$upscope $end
$scope module or3 $end
$var wire 1 f a $end
$var wire 1 , b $end
$var wire 1 + c $end
$var wire 1 * d $end
$var wire 1 ) e $end
$var wire 1 g y $end
$upscope $end
$scope module sum0 $end
$var wire 1 h a $end
$var wire 1 i b $end
$var wire 1 j y $end
$upscope $end
$scope module sum1 $end
$var wire 1 k a $end
$var wire 1 l b $end
$var wire 1 m y $end
$upscope $end
$scope module sum2 $end
$var wire 1 n a $end
$var wire 1 o b $end
$var wire 1 p y $end
$upscope $end
$scope module sum3 $end
$var wire 1 q a $end
$var wire 1 r b $end
$var wire 1 s y $end
$upscope $end
$scope module xor0 $end
$var wire 1 t a $end
$var wire 1 u b $end
$var wire 1 v y $end
$upscope $end
$scope module xor1 $end
$var wire 1 w a $end
$var wire 1 x b $end
$var wire 1 y y $end
$upscope $end
$scope module xor2 $end
$var wire 1 z a $end
$var wire 1 { b $end
$var wire 1 | y $end
$upscope $end
$scope module xor3 $end
$var wire 1 } a $end
$var wire 1 ~ b $end
$var wire 1 !" y $end
$upscope $end
$upscope $end
$upscope $end
$enddefinitions $end
$comment Show the parameter values. $end
$dumpall
$end
#0
$dumpvars
0!"
0~
0}
0|
0{
0z
0y
0x
0w
0v
0u
0t
0s
0r
0q
0p
0o
0n
0m
0l
0k
0j
0i
0h
0g
0f
0e
0d
0c
0b
0a
0`
0_
0^
0]
0\
0[
0Z
0Y
0X
0W
0V
0U
0T
0S
0R
0Q
0P
0O
0N
0M
0L
0K
0J
0I
0H
0G
0F
0E
0D
0C
0B
0A
0@
0?
0>
0=
0<
0;
0:
09
08
07
06
b0 5
b0 4
b0 3
02
01
00
0/
0.
0-
0,
0+
0*
0)
b0 (
b0 '
b0 &
0%
b0 $
b0 #
b0 "
b0 !
$end
#30
1m
b11 !
b11 (
1j
1R
1T
1Z
1]
1C
1G
1k
1P
1U
1^
1H
1h
1y
b11 3
1v
1:
1x
16
1t
b10 $
b10 '
b1 #
b1 &
#40
1s
1r
1e
1p
0m
1o
1l
1c
1a
1d
1=
b1100 !
b1100 (
0j
10
12
b100 4
1L
1i
1I
1_
1V
1Q
1K
1{
1J
1z
b1111 "
b1111 5
1%
b110 $
b110 '
b101 #
b101 &
#50
1g
1*
1o
11
1.
0p
0s
1c
1`
1S
1[
1D
0d
0=
0P
0U
0^
0H
0h
1W
1Y
1\
1?
1B
1F
1n
1<
1>
1A
1E
1q
b0 !
b0 (
0j
00
02
18
b1 4
0L
0v
1|
b1110 3
1!"
0i
0I
0_
0V
0Q
17
0:
0K
1u
0x
0{
19
1M
1w
1}
b11110 "
b11110 5
0%
b1 $
b1 '
b1111 #
b1111 &
#60
10
1-
1)
01
0.
0*
12
0`
0S
0[
0D
1P
1U
1^
1H
1h
b0 !
b0 (
0j
b0 4
08
b1111 3
1v
1i
1I
1_
1V
1Q
1K
1{
06
0J
0t
0z
b11111 "
b11111 5
1%
b101 $
b101 '
b1010 #
b1010 &
#70
1s
1p
1m
0r
0o
0l
0g
0e
0c
0a
b1111 !
b1111 (
1j
0)
0-
00
02
0i
0I
0_
0V
0Q
1:
0K
1x
0{
09
1J
0w
1z
b0 "
b0 5
0%
b11 $
b11 '
b1100 #
b1100 &
#80
0s
0p
0m
1r
1o
1l
1g
1e
1c
1a
b0 !
b0 (
0j
1)
1-
10
12
1i
1I
1_
1V
1Q
07
1K
0u
1{
16
0J
1t
0z
b11111 "
b11111 5
1%
b110 $
b110 '
b1001 #
b1001 &
#90
1r
1o
1s
1m
1p
1g
1e
1c
1`
1S
1[
1D
1f
0P
0U
0^
0H
0h
0<
0>
0A
0E
0q
1b
1X
1@
1d
1=
0R
0T
0Z
0]
0C
0G
0k
0W
0Y
0\
0?
0B
0F
0n
b1110 !
b1110 (
0j
0)
0-
00
02
18
1O
0v
0!"
1;
b1111 4
1L
0y
b0 3
0|
0i
0I
0_
0V
0Q
17
1N
1u
1~
19
1J
1w
1z
b11110 "
b11110 5
0%
b1111 $
b1111 '
b1111 #
b1111 &
#100
b1111 !
b1111 (
1j
1i
1I
1_
1V
1Q
b11111 "
b11111 5
1%
#110
0s
0p
0r
0g
0m
0o
0e
0l
0c
0a
0`
0S
0[
0D
0b
0X
0@
0d
0=
0f
b0 !
b0 (
0j
08
0;
0L
b0 4
0O
0i
0I
0_
0V
0Q
07
0:
0K
0N
0u
0x
0{
0~
06
09
0J
0M
0t
0w
0z
0}
b0 "
b0 5
0%
b0 $
b0 '
b0 #
b0 &
#120
b1 !
b1 (
1j
1i
1I
1_
1V
1Q
b1 "
b1 5
1%
#130
1m
1l
1a
1`
1S
1[
1D
b10 !
b10 (
0j
b1 4
18
0i
0I
0_
0V
0Q
17
1u
16
1t
b10 "
b10 5
0%
b1 $
b1 '
b1 #
b1 &
#140
b11 !
b11 (
1j
1i
1I
1_
1V
1Q
b11 "
b11 5
1%
#150
1p
0m
1o
0l
1c
0a
0`
0S
0[
0D
1b
1X
1@
b100 !
b100 (
0j
08
b10 4
1;
0i
0I
0_
0V
0Q
07
1:
0u
1x
06
19
0t
1w
b100 "
b100 5
0%
b10 $
b10 '
b10 #
b10 &
#160
b101 !
b101 (
1j
1i
1I
1_
1V
1Q
b101 "
b101 5
1%
#170
1m
1l
1a
1`
1S
1[
1D
b110 !
b110 (
0j
b11 4
18
0i
0I
0_
0V
0Q
17
1u
16
1t
b110 "
b110 5
0%
b11 $
b11 '
b11 #
b11 &
#180
b111 !
b111 (
1j
1i
1I
1_
1V
1Q
b111 "
b111 5
1%
#190
1s
0p
1r
0m
0o
1e
0l
0c
0a
0`
0S
0[
0D
0b
0X
0@
1d
1=
b1000 !
b1000 (
0j
08
0;
b100 4
1L
0i
0I
0_
0V
0Q
07
0:
1K
0u
0x
1{
06
09
1J
0t
0w
1z
b1000 "
b1000 5
0%
b100 $
b100 '
b100 #
b100 &
#200
b1001 !
b1001 (
1j
1i
1I
1_
1V
1Q
b1001 "
b1001 5
1%
