verilog/dffwithand.v
module dff (
    input clk,
    input d,
    output q
);
    wire d_latch_out, q_latch_out;
    wire clk_n;

    not u_not (clk_n, clk);

    latch master_latch (
        .clk(clk_n),
        .d(d),
        .q(d_latch_out)
    );

    latch slave_latch (
        .clk(clk),
        .d(d_latch_out),
        .q(q_latch_out)
    );

    assign q = q_latch_out;

endmodule

module latch (
    input clk,
    input d,
    output q
);
    wire nand1_out, nand2_out, nand3_out, nand4_out;

    nand u_nand1 (nand1_out, d, clk);
    nand u_nand2 (nand2_out, nand1_out, clk);
    nand u_nand3 (nand3_out, nand2_out, nand4_out);
    nand u_nand4 (nand4_out, nand3_out, nand1_out);

    assign q = nand3_out;

endmodule

verilog/dffwithnandtb.v
module test_dff;
    reg clk;
    reg d;
    wire q;

    dff uut (
        .clk(clk),
        .d(d),
        .q(q)
    );

    initial begin
        clk = 1;
        forever #5 clk = ~clk; 
    end

    initial begin
        d = 0;

        #8 d = 1;
        #8 d = 0;
        #8 d = 1;
        #8 d = 0;
        #20 $finish;
    end

    initial begin
        $monitor("At time %t, clk = %b, d = %b, q = %b", $time, clk, d, q);
    end
     initial begin
        $dumpfile("dffwithnand.vcd");
        $dumpvars(0, test_dff);
    end
endmodule

verilog/dffwithnand.vcd
$date
	Wed Nov 20 15:14:24 2024
$end
$version
	Icarus Verilog
$end
$timescale
	1s
$end
$scope module test_dff $end
$var wire 1 ! q $end
$var reg 1 " clk $end
$var reg 1 # d $end
$scope module uut $end
$var wire 1 " clk $end
$var wire 1 $ clk_n $end
$var wire 1 # d $end
$var wire 1 ! q $end
$var wire 1 % q_latch_out $end
$var wire 1 & d_latch_out $end
$scope module master_latch $end
$var wire 1 $ clk $end
$var wire 1 # d $end
$var wire 1 ' nand1_out $end
$var wire 1 ( nand2_out $end
$var wire 1 ) nand3_out $end
$var wire 1 * nand4_out $end
$var wire 1 & q $end
$upscope $end
$scope module slave_latch $end
$var wire 1 " clk $end
$var wire 1 & d $end
$var wire 1 + nand1_out $end
$var wire 1 , nand2_out $end
$var wire 1 - nand3_out $end
$var wire 1 . nand4_out $end
$var wire 1 % q $end
$upscope $end
$upscope $end
$upscope $end
$enddefinitions $end
$comment Show the parameter values. $end
$dumpall
$end
#0
$dumpvars
x.
x-
x,
x+
x*
x)
1(
1'
x&
x%
0$
0#
1"
x!
$end
#5
0*
1&
1)
0(
1$
1+
1,
0"
#8
0&
0)
1(
1*
0'
1#
#10
0.
1'
1!
1%
1-
0$
0,
1"
#15
0&
0)
0'
1(
1$
1,
0"
#16
0*
1&
1)
0(
1'
0#
#20
0!
0%
0-
1(
1.
0$
0+
1,
1"
#24
1#
#25
0&
0)
1*
0'
1(
1$
1+
0"
#30
0.
1'
1!
1%
1-
0$
0,
1"
#32
0#
#35
0*
1&
1)
0(
1$
1,
0"
#40
0!
0%
0-
1(
1.
0$
0+
1,
1"
#45
0(
1$
1+
0"
#50
1(
0!
0%
0-
0$
0+
1,
1"
